product_apriori/__init__.py
product_apriori/main.py
product_apriori-1.0.1.dist-info/METADATA
product_apriori-1.0.1.dist-info/WHEEL
product_apriori-1.0.1.dist-info/entry_points.txt
product_apriori-1.0.1.dist-info/licenses/LICENSE
product_apriori-1.0.1.dist-info/RECORD
