Metadata-Version: 2.1
Name: product_apriori
Version: 1.0.1
Summary: Apriori product relation test
Project-URL: Homepage, https://github.com/joycecpy1025/procurement/tree/joyce/projects/analytics/product_relation
Author-email: joyce_chan <joyce.chan@mrdiy.com>, william_cheah <william.cheah@mrdiy.com>
License: MIT License
License-File: LICENSE
Classifier: License :: OSI Approved :: MIT License
Classifier: Programming Language :: Python
Classifier: Programming Language :: Python :: 3
Requires-Python: >=3.9
Requires-Dist: feedparser>=5.2.0
Requires-Dist: tomli; python_version < '3.11'
